<annotation>
  <folder>images</folder>
  <filename>13a151aea1e8f432.jpg</filename>
  <path>C:\Users\chuaz\test-videoio\nanodet\data\dataset\googleOI_dataset\mobile phone\images\13a151aea1e8f432.jpg</path>
  <source>
    <database>OpenImages</database>
  </source>
  <size>
    <width>1024</width>
    <height>683</height>
    <depth>3</depth>
  </size>
  <segmented>0</segmented>
  <object>
    <name>mobile phone</name>
    <pose>Unspecified</pose>
    <truncated>0</truncated>
    <difficult>0</difficult>
    <bndbox>
      <xmin>176</xmin>
      <xmax>513</xmax>
      <ymin>40</ymin>
      <ymax>649</ymax>
    </bndbox>
  </object>
  <object>
    <name>mobile phone</name>
    <pose>Unspecified</pose>
    <truncated>0</truncated>
    <difficult>0</difficult>
    <bndbox>
      <xmin>478</xmin>
      <xmax>590</xmax>
      <ymin>240</ymin>
      <ymax>501</ymax>
    </bndbox>
  </object>
  <object>
    <name>mobile phone</name>
    <pose>Unspecified</pose>
    <truncated>0</truncated>
    <difficult>0</difficult>
    <bndbox>
      <xmin>574</xmin>
      <xmax>666</xmax>
      <ymin>225</ymin>
      <ymax>441</ymax>
    </bndbox>
  </object>
</annotation>
