<annotation>
  <folder>images</folder>
  <filename>0009d6b2e2f0c698.jpg</filename>
  <path>C:\Users\chuaz\test-videoio\nanodet\nanodet\data\dataset\simple_data\bottle\images\0009d6b2e2f0c698.jpg</path>
  <source>
    <database>OpenImages</database>
  </source>
  <size>
    <width>1024</width>
    <height>683</height>
    <depth>3</depth>
  </size>
  <segmented>0</segmented>
  <object>
    <name>bottle123</name>
    <pose>Unspecified</pose>
    <truncated>0</truncated>
    <difficult>0</difficult>
    <bndbox>
      <xmin>281</xmin>
      <xmax>310</xmax>
      <ymin>429</ymin>
      <ymax>501</ymax>
    </bndbox>
  </object>
  <object>
    <name>bottle123</name>
    <pose>Unspecified</pose>
    <truncated>0</truncated>
    <difficult>0</difficult>
    <bndbox>
      <xmin>335</xmin>
      <xmax>377</xmax>
      <ymin>363</ymin>
      <ymax>476</ymax>
    </bndbox>
  </object>
  <object>
    <name>bottle123</name>
    <pose>Unspecified</pose>
    <truncated>0</truncated>
    <difficult>0</difficult>
    <bndbox>
      <xmin>463</xmin>
      <xmax>491</xmax>
      <ymin>399</ymin>
      <ymax>461</ymax>
    </bndbox>
  </object>
</annotation>
